pinyinlize/__init__.py
pinyinlize/main_script.py
pinyinlize-0.2.1.dist-info/LICENSE
pinyinlize-0.2.1.dist-info/METADATA
pinyinlize-0.2.1.dist-info/WHEEL
pinyinlize-0.2.1.dist-info/entry_points.txt
pinyinlize-0.2.1.dist-info/top_level.txt
pinyinlize-0.2.1.dist-info/RECORD
