Metadata-Version: 2.1
Name: pinyinlize
Version: 0.2.1
Summary: a package converts short Chinese-character strings(titles of books, articles or journals) to pinyin.
Author-email: Fei Guo <fguogufe2@gmail.com>
Keywords: pinyin,Chinese,title,journal,book
Classifier: Programming Language :: Python :: 3
Classifier: License :: OSI Approved :: MIT License
Classifier: Operating System :: OS Independent
License-File: LICENSE
Requires-Dist: jieba
Requires-Dist: pypinyin
